fnsafe.py
fnsafe-0.0.1.post1.dist-info/METADATA
fnsafe-0.0.1.post1.dist-info/WHEEL
fnsafe-0.0.1.post1.dist-info/top_level.txt
fnsafe-0.0.1.post1.dist-info/RECORD
