Metadata-Version: 2.1
Name: fnsafe
Version: 0.0.1.post1
Summary: Not raising functions - like rust.
License: MIT
Keywords: error,exception,function,functional,raise,rust,safe
Classifier: Development Status :: 5 - Production/Stable
Classifier: Intended Audience :: Developers
Classifier: License :: OSI Approved :: MIT License
Classifier: Natural Language :: English
Classifier: Programming Language :: Python :: Implementation :: CPython
Classifier: Programming Language :: Rust
Classifier: Topic :: Utilities
Classifier: Typing :: Typed
